broadworks_django_auth/__init__.py
broadworks_django_auth/admin.py
broadworks_django_auth/apps.py
broadworks_django_auth/backends.py
broadworks_django_auth/models.py
broadworks_django_auth/tests.py
broadworks_django_auth/migrations/0001_initial.py
broadworks_django_auth/migrations/0002_auto_20191202_1556.py
broadworks_django_auth/migrations/__init__.py
Broadworks_Django_Authentication-0.0.1.dist-info/LICENSE
Broadworks_Django_Authentication-0.0.1.dist-info/METADATA
Broadworks_Django_Authentication-0.0.1.dist-info/WHEEL
Broadworks_Django_Authentication-0.0.1.dist-info/top_level.txt
Broadworks_Django_Authentication-0.0.1.dist-info/RECORD
