Metadata-Version: 2.1
Name: Broadworks-Django-Authentication
Version: 0.0.1
Summary: Broadworks Authentication for your django app
Home-page: UNKNOWN
Author: Aaron Parfitt
Author-email: aaronparfitt123@gmail.com
License: UNKNOWN
Keywords: Broadworks,Django
Platform: UNKNOWN
Classifier: Framework :: Django :: 2.1
Classifier: Development Status :: 3 - Alpha
Requires-Dist: BroadworksOCIP
